RW_S3/S3Reader.py
RW_S3/S3Writer.py
RW_S3/__init__.py
RW_S3/read_s3.py
RW_S3/write_s3.py
RW_S3-0.0.7.dist-info/METADATA
RW_S3-0.0.7.dist-info/WHEEL
RW_S3-0.0.7.dist-info/top_level.txt
RW_S3-0.0.7.dist-info/RECORD
