Metadata-Version: 2.1
Name: RW-S3
Version: 0.0.7
Summary: UNKNOWN
Home-page: https://github.com/mynkit/RW_S3
Author: mynkit
Author-email: dcm5124289@gmail.com
License: UNKNOWN
Platform: UNKNOWN
Requires-Python: >=3.5
Requires-Dist: pandas
Requires-Dist: xlrd
Requires-Dist: boto3
